cdd_python_sdk/VaultClient.py
cdd_python_sdk/__init__.py
cdd_python_sdk/help_docs/get_ELN_entries.txt
cdd_python_sdk/help_docs/get_api_execution_metrics.txt
cdd_python_sdk/help_docs/get_batches.txt
cdd_python_sdk/help_docs/get_collections.txt
cdd_python_sdk/help_docs/get_molecules.txt
cdd_python_sdk/help_docs/get_plates.txt
cdd_python_sdk/help_docs/get_protocol_data.txt
cdd_python_sdk/help_docs/get_protocols.txt
cdd_python_sdk/help_docs/get_readout_rows.txt
cdd_python_sdk/help_docs/get_runs.txt
cdd_python_sdk/help_docs/get_sample_inventory.txt
cdd_python_sdk/help_docs/get_saved_searches.txt
cdd_python_sdk/help_docs/get_users.txt
cdd_python_sdk/help_docs/post_batch_move_job.txt
cdd_python_sdk/help_docs/post_batches.txt
cdd_python_sdk/help_docs/post_inventory_samples.txt
cdd_python_sdk/help_docs/post_molecules.txt
cdd_python_sdk/help_docs/put_eln_entries.txt
cdd_python_sdk/help_docs/put_molecules.txt
cdd_python_sdk/help_docs/put_plates.txt
cdd_python_sdk-1.0.6.dist-info/licenses/LICENSE
cdd_python_sdk-1.0.6.dist-info/METADATA
cdd_python_sdk-1.0.6.dist-info/WHEEL
cdd_python_sdk-1.0.6.dist-info/top_level.txt
cdd_python_sdk-1.0.6.dist-info/RECORD
