Metadata-Version: 2.4
Name: cdd_python_sdk
Version: 1.0.6
Summary: A Python client for streamlined execution of CDD Vault API methods.
Author-email: Gerard Mattei <gerry.mattei@workflowinformatics.com>, Ryan Moore <ryan.moore@workflowinformatics.com>
Classifier: Programming Language :: Python :: 3
Classifier: License :: OSI Approved :: GNU General Public License (GPL)
Classifier: Operating System :: OS Independent
Requires-Python: >=3.8
License-File: LICENSE
Dynamic: license-file
